{
  "schemaVersion": 1,
  "kind": "sdkwork.component.spec",
  "component": {
    "name": "@sdkwork/birdcoder-pc-console-core",
    "displayName": "SDKWork Birdcoder PC Console Core",
    "version": "0.1.0",
    "type": "typescript-package",
    "root": "sdkwork-birdcoder/apps/sdkwork-birdcoder-pc/packages/sdkwork-birdcoder-pc-console-core",
    "domain": "platform",
    "capability": "console-core",
    "surface": "console",
    "languages": [
      "typescript"
    ],
    "generated": false,
    "private": true,
    "manifests": [
      "package.json"
    ]
  },
  "contracts": {
    "publicExports": [
      "."
    ],
    "sdkClients": [],
    "sdkDependencies": [
      {
        "workspace": "sdkwork-birdcoder-app-sdk",
        "surface": "app-api",
        "credentialMode": "authenticated-app-api"
      },
      {
        "workspace": "sdkwork-birdcoder-app-sdk-typescript",
        "surface": "open-api",
        "credentialMode": "protected-open-api-flexible"
      },
      {
        "workspace": "sdkwork-drive-app-sdk",
        "surface": "app-api",
        "credentialMode": "authenticated-app-api"
      },
      {
        "workspace": "sdkwork-drive-app-sdk-typescript",
        "surface": "open-api",
        "credentialMode": "protected-open-api-flexible"
      },
      {
        "workspace": "sdkwork-iam-app-sdk",
        "surface": "app-api",
        "credentialMode": "authenticated-app-api"
      },
      {
        "workspace": "sdkwork-iam-app-sdk-typescript",
        "surface": "open-api",
        "credentialMode": "protected-open-api-flexible"
      },
      {
        "workspace": "sdkwork-messaging-app-sdk",
        "surface": "app-api",
        "credentialMode": "authenticated-app-api"
      },
      {
        "workspace": "sdkwork-messaging-app-sdk-typescript",
        "surface": "open-api",
        "credentialMode": "protected-open-api-flexible"
      }
    ],
    "permissionComposition": {
      "inheritanceMode": "module-catalog-with-overrides",
      "applicationModule": {
        "manifestRef": "../../../../../specs/iam.module.manifest.json"
      },
      "moduleCatalogRefs": [
        {
          "moduleId": "drive",
          "manifestRef": "../../../../../../sdkwork-iam/iam/modules/drive/iam.module.manifest.json",
          "inheritPermissions": true,
          "inheritRoles": true
        },
        {
          "moduleId": "iam-kernel",
          "manifestRef": "../../../../../../sdkwork-iam/iam/modules/iam-kernel/iam.module.manifest.json",
          "inheritPermissions": true,
          "inheritRoles": false
        },
        {
          "moduleId": "messaging",
          "manifestRef": "../../../../../../sdkwork-iam/iam/modules/messaging/iam.module.manifest.json",
          "inheritPermissions": true,
          "inheritRoles": true
        },
        {
          "moduleId": "birdcoder",
          "manifestRef": "../../../../../specs/iam.module.manifest.json",
          "inheritPermissions": true,
          "inheritRoles": true
        }
      ],
      "bootstrapAccessTokenScope": {
        "inheritFrom": "sdkwork.app.config.json#backend.accessTokenPermissionScope",
        "supplement": [],
        "overrideReplace": false
      },
      "routePermissionHints": {
        "inheritFromOpenApi": true,
        "inheritFromModuleManifests": true,
        "overrides": []
      },
      "consumerPolicy": {
        "forbidLocalPermissionCatalogForDependencyDomains": true,
        "allowExplicitOverridesOnly": true,
        "allowFrontendHintsWithoutServerDuplication": true
      }
    }
  }
}
